patchlib/__init__.py
patchlib/bps.py
patchlib/eps.py
patchlib/ips.py
get_patchlib-1.6.dist-info/LICENSE
get_patchlib-1.6.dist-info/METADATA
get_patchlib-1.6.dist-info/WHEEL
get_patchlib-1.6.dist-info/top_level.txt
get_patchlib-1.6.dist-info/RECORD
