Metadata-Version: 2.1
Name: get-patchlib
Version: 1.6
Summary: Patch file handler
Home-page: https://github.com/BrettefromNesUniverse/patchlib
Author: Brette
License: MIT
Keywords: Patch file handler
Classifier: Programming Language :: Python :: 3
Classifier: License :: OSI Approved :: MIT License
Classifier: Operating System :: OS Independent
Requires-Python: >=3.7
License-File: LICENSE
Provides-Extra: docs
Requires-Dist: sphinx ; extra == 'docs'
